MANIFEST.in
README.md
setup.py
allo/__init__.py
allo/cmd.py
allo/const.py
allo/changes/__init__.py
allo/changes/commands.py
allo/install/__init__.py
allo/install/commands.py
allo/model/channel.py
allo/model/colors.py
allo/model/config.py
allo/model/version.py
allo/telem/__init__.py
allo/telem/commands.py
allo/telem/telem.py
allo/update/__init__.py
allo/update/commands.py
allo/utils/ansible.py
allo/utils/api.py
allo/utils/configloader.py
allo/utils/git.py
allo/utils/logreader.py
allo/utils/playbooks/create_user.yml
allo/utils/playbooks/install_allo.yml
allo/utils/playbooks/start_service.yml
allo/utils/playbooks/stop_service.yml
allo/utils/playbooks/install/RedHat-7.yml
allo/utils/playbooks/install/RedHat-8.yml
allo/utils/playbooks/install/allo_instanceinfos.sh
allo/utils/playbooks/install/default-Debian.yml
allo/utils/playbooks/install/default-RedHat.yml
allo/utils/playbooks/install/default.yml
allo_client.beta.egg-info/PKG-INFO
allo_client.beta.egg-info/SOURCES.txt
allo_client.beta.egg-info/dependency_links.txt
allo_client.beta.egg-info/entry_points.txt
allo_client.beta.egg-info/requires.txt
allo_client.beta.egg-info/top_level.txt