Metadata-Version: 2.1
Name: allo-client.beta
Version: 0.0.1.post161674
Summary: Libriciel upgrade package
Home-page: https://gitlab.libriciel.fr/libriciel/projets-internes/allo/allo-client
Author: Lukas Hameury
Author-email: lukas.hameury@libriciel.coop
License: UNKNOWN
Platform: UNKNOWN
